convert_source/__init__.py
convert_source/batch_convert.py
convert_source/version.txt
convert_source/bin/study_proc
convert_source/config/bids_version.txt
convert_source/config/config.CCHMC.default.yml
convert_source/config/config.default.yml
convert_source/config/config.template.yml
convert_source/config/example.config.yml
convert_source/cs_utils/__init__.py
convert_source/cs_utils/bids_info.py
convert_source/cs_utils/const.py
convert_source/cs_utils/fileio.py
convert_source/cs_utils/img_dir.py
convert_source/cs_utils/utils.py
convert_source/imgio/__init__.py
convert_source/imgio/dcmio.py
convert_source/imgio/niio.py
convert_source/imgio/pario.py
convert_source-0.1.1.data/scripts/study_proc
convert_source-0.1.1.dist-info/LICENSE
convert_source-0.1.1.dist-info/METADATA
convert_source-0.1.1.dist-info/WHEEL
convert_source-0.1.1.dist-info/top_level.txt
convert_source-0.1.1.dist-info/RECORD
