Metadata-Version: 2.1
Name: convert-source
Version: 0.1.1
Summary: Converts and organises source MR image data-sets in accordance with the Brain Imaging Data Structure (BIDS)
Home-page: https://github.com/AdebayoBraimah/convert_source
Author: Adebayo Braimah
Author-email: adebayo.braimah@cchmc.org
License: GPL-3.0 License
Keywords: bids mri imaging neuroimaging dicom par rec nifti
Platform: UNKNOWN
Classifier: Intended Audience :: Science/Research
Classifier: Natural Language :: English
Classifier: License :: OSI Approved :: GNU General Public License v3 (GPLv3)
Classifier: Operating System :: OS Independent
Classifier: Programming Language :: Python :: 3
Requires-Python: >=3.7
Requires-Dist: numpy (>=1.18.5)
Requires-Dist: pydicom (>=2.1.2)
Requires-Dist: nibabel (>=3.2.1)
Requires-Dist: PyYAML (>=5.3.1)
Requires-Dist: pandas (>=1.0.5)
